shipitscript/__init__.py
shipitscript/script.py
shipitscript/ship_actions.py
shipitscript/task.py
shipitscript/utils.py
shipitscript/data/mark_as_shipped_task_schema.json
shipitscript/data/mark_as_started_task_schema.json
shipitscript/data/task.example.json
shipitscript/test/__init__.py
shipitscript/test/test_script.py
shipitscript/test/test_ship_actions.py
shipitscript/test/test_task.py
shipitscript/test/test_utils.py
shipitscript/test/integration/__init__.py
shipitscript/test/integration/test_integration_script.py
shipitscript-3.2.0.dist-info/LICENSE
shipitscript-3.2.0.dist-info/METADATA
shipitscript-3.2.0.dist-info/WHEEL
shipitscript-3.2.0.dist-info/entry_points.txt
shipitscript-3.2.0.dist-info/top_level.txt
shipitscript-3.2.0.dist-info/RECORD
