Metadata-Version: 2.1
Name: shipitscript
Version: 3.2.0
Summary: TaskCluster Ship-It Worker
Home-page: https://github.com/mozilla-releng/shipitscript
Author: Mozilla Release Engineering
Author-email: release+python@mozilla.com
License: MPL2
Platform: UNKNOWN
Classifier: Programming Language :: Python :: 3.6
Classifier: Programming Language :: Python :: 3.7
Requires-Dist: scriptworker
Requires-Dist: shipitapi (>=2.1.0)
